starlink_grpc.py
starlink_grpc_core-1.2.3.dist-info/licenses/LICENSE
starlink_grpc_core-1.2.3.dist-info/METADATA
starlink_grpc_core-1.2.3.dist-info/WHEEL
starlink_grpc_core-1.2.3.dist-info/top_level.txt
starlink_grpc_core-1.2.3.dist-info/RECORD
