Metadata-Version: 2.4
Name: starlink-grpc-core
Version: 1.2.3
Summary: Core functions for Starlink gRPC communication
Home-page: https://github.com/sparky8512/starlink-grpc-tools
Author-email: sparky8512-py@yahoo.com
Classifier: Development Status :: 4 - Beta
Classifier: Intended Audience :: Developers
Classifier: License :: OSI Approved :: The Unlicense (Unlicense)
Classifier: Operating System :: OS Independent
Classifier: Programming Language :: Python :: 3
Classifier: Topic :: Software Development :: Libraries :: Python Modules
Requires-Python: >=3.7
License-File: LICENSE
Requires-Dist: grpcio>=1.12.0
Requires-Dist: protobuf>=3.6.0
Requires-Dist: yagrc>=1.1.1
Requires-Dist: typing-extensions>=4.3.0
Dynamic: license-file
